README.rst
setup.cfg
setup.py
pyinsta_dl/__init__.py
pyinsta_dl.egg-info/PKG-INFO
pyinsta_dl.egg-info/SOURCES.txt
pyinsta_dl.egg-info/dependency_links.txt
pyinsta_dl.egg-info/not-zip-safe
pyinsta_dl.egg-info/requires.txt
pyinsta_dl.egg-info/top_level.txt