Metadata-Version: 1.0
Name: pyinsta-dl
Version: 0.1.4
Summary: Python implementation for download images and videos from Instagram
Home-page: https://github.com/natanocr/pyinsta_dl
Author: Natan Oliveira
Author-email: natanoliveiracruz@gmail.com
License: MIT
Keywords: instagram download media image video
Platform: Linux
